seedpy/__init__.py
seedpy/const.py
seedpy/seed.py
seedpy/test.py
seedpy-1.0.0.dist-info/LICENSE
seedpy-1.0.0.dist-info/METADATA
seedpy-1.0.0.dist-info/WHEEL
seedpy-1.0.0.dist-info/top_level.txt
seedpy-1.0.0.dist-info/RECORD
