Metadata-Version: 2.1
Name: seedpy
Version: 1.0.0
Summary: kisa seed encryption and decryption
Home-page: https://github.com/blluv/seed_py
Author: blluv
Author-email: biluv@protonmail.com
License: MIT
Platform: UNKNOWN
